hurry_ai/__init__.py
hurry_ai/ai.py
hurry_ai-0.0.3.dist-info/LICENSE
hurry_ai-0.0.3.dist-info/METADATA
hurry_ai-0.0.3.dist-info/WHEEL
hurry_ai-0.0.3.dist-info/top_level.txt
hurry_ai-0.0.3.dist-info/RECORD
