Metadata-Version: 2.1
Name: hurry-ai
Version: 0.0.3
Summary: Hurry: Confidently ship on a Friday with a clean LLM interface
Home-page: https://github.com/thoriqakbar0/hurry
Author: Thoriq Akbar
Author-email: thoriqakbar00@gmail.com
Classifier: Programming Language :: Python :: 3
Classifier: License :: OSI Approved :: MIT License
Classifier: Operating System :: OS Independent
Requires-Python: >=3.9
License-File: LICENSE
Requires-Dist: instructor
Requires-Dist: openai
